ipahcc/__init__.py
ipahcc/_version.py
ipahcc/hccplatform.py
ipahcc/py.typed
ipahcc/client/__init__.py
ipahcc/client/auto_enrollment.py
ipahcc/client/client_prepare.py
ipahcc/client/stage_console.py
ipahcc/server/__init__.py
ipahcc/server/cli.py
ipahcc/server/domain_token.py
ipahcc/server/framework.py
ipahcc/server/hccapi.py
ipahcc/server/mockapi.py
ipahcc/server/registration.py
ipahcc/server/schema.py
ipahcc/server/util.py
ipahcc/server/schema/defs.json
ipahcc/server/schema/domain_reg_token_request.json
ipahcc/server/schema/domain_reg_token_response.json
ipahcc/server/schema/errors.json
ipahcc/server/schema/host_conf_request.json
ipahcc/server/schema/host_conf_response.json
ipahcc/server/schema/host_register_request.json
ipahcc/server/schema/host_register_response.json
ipahcc/server/schema/ipadomain_get_request.json
ipahcc/server/schema/ipadomain_register_request.json
ipahcc/server/schema/ipadomain_register_response.json
ipahcc/server/schema/ipadomain_update_request.json
ipahcc/server/schema/ipadomain_update_response.json
ipahcc/server/schema/signing_keys_response.json
ipahcc/server/sign/__init__.py
ipahcc/server/sign/__main__.py
ipahcc/server/sign/_jwk.py
ipahcc/server/sign/_jwst.py
ipaserver/install/plugins/update_hcc.py
ipaserver/install/plugins/update_hcc_enrollment_service.py
ipaserver/install/plugins/update_hcc_mockapi.py
ipaserver/plugins/hccconfig.py
ipaserver/plugins/hcchost.py
ipaserver/plugins/hccidp.py
ipaserver/plugins/hccjwk.py
ipaserver/plugins/hccserverroles.py
ipahcc-0.17.dist-info/COPYING
ipahcc-0.17.dist-info/METADATA
ipahcc-0.17.dist-info/WHEEL
ipahcc-0.17.dist-info/entry_points.txt
ipahcc-0.17.dist-info/top_level.txt
ipahcc-0.17.dist-info/RECORD
