Metadata-Version: 2.1
Name: ipahcc
Version: 0.17
Summary: IPA enrollment agent for Red Hat Hybrid Cloud Console
Author: Christian Heimes
Author-email: Christian Heimes <cheimes@redhat.com>
License: GPL-3.0-or-later
Platform: any
Requires-Python: >=3.6
License-File: COPYING
Requires-Dist: requests
Requires-Dist: ipalib
Requires-Dist: netaddr <1.0.0 ; python_version == "3.6"
Provides-Extra: server
Requires-Dist: cryptography ; extra == 'server'
Requires-Dist: ipaclient ; extra == 'server'
Requires-Dist: jsonschema ; extra == 'server'
Requires-Dist: jwcrypto ; extra == 'server'
